[
  {
    "namespace": "displayReceivedHeader",
    "functions": [
      {
        "name": "setReceivedHeaderHidden",
        "description": "Set hidden attribute to the Received header",
        "type": "function",
        "parameters": [
          {
            "name": "windowId",
            "type": "integer"
          },
          {
            "name": "tabIndex",
            "type": "integer"
          },
          {
            "name": "hidden",
            "description": "Hidden attribute value",
            "type": "boolean"
          }
        ]
      },
      {
        "name": "setReceivedHeaderValue",
        "description": "Update the Received header value",
        "type": "function",
        "parameters": [
          {
            "name": "windowId",
            "type": "integer"
          },
          {
            "name": "tabIndex",
            "type": "integer"
          },
          {
            "name": "headersArray",
            "description": "Array of Received headers",
            "type": "array",
            "items": {
              "type": "array",
              "items": {
                "type": "string"
              }
            }
          },
          {
            "name": "singleLine",
            "description": "List all headers on a single line",
            "type": "boolean"
          },
          {
            "name": "separator",
            "description": "Single line items separator string",
            "type": "string"
          }
        ]
      }
    ]
  }
]
